[{
    "id": 5,
    "name": "Банановый пирог",
    "imgSmall": "img/5_small.jpg",
    "rating": 8,
    "tags": [ "сладкое", "горячее", "выпечка" ],
    "ingredients": [ "масло", "мука", "яйца", "сгущёнка", "сахар" ]
}, {
    "id": 1,
    "name": "Гравские развалины",
    "imgSmall": "img/1_small.jpg",
    "rating": 9,
    "tags": [ "сладкое", "холодное", "выпечка" ],
    "ingredients": [ "масло", "мука", "ванилин", "сахар", "яйца", "какао", "сметана" ]
}, {
    "id": 3,
    "name": "Наполеон",
    "imgSmall": "img/3_small.jpg",
    "rating": 8,
    "tags": [ "сладкое", "холодное", "выпечка" ],
    "ingredients": [ "масло", "мука", "яйца", "маргарин", "соль", "молоко", "ванилин", "сахар" ]
}, {
    "id": 4,
    "name": "Шоколадно-творожный пирог",
    "imgSmall": "img/4_small.jpg",
    "rating": 7,
    "tags": [ "сладкое", "горячее", "выпечка" ],
    "ingredients": [ "масло", "мука", "яйца", "сгущёнка", "сахар" ]
}, {
    "id": 2,
    "name": "Яблочная запеканка",
    "imgSmall": "img/2_small.jpg",
    "rating": 9,
    "tags": [ "сладкое", "горячее", "выпечка" ],
    "ingredients": [ "масло", "мука", "яйца", "сгущёнка", "сахар" ]
}]